[
  {
    "Id": "1090256",
    "ThreadId": "456252",
    "Html": "FYI - When I am in the &quot;Manage Catalog Subscription&quot; screen and click on the &quot;Check Update Availability Now&quot; button, the response is in French instead of English.   &quot;Aucune mise a jour disponible&quot;.<br />\n",
    "PostedDate": "2013-09-09T09:30:16.64-07:00",
    "UserRole": null,
    "MarkedAsAnswerDate": null
  },
  {
    "Id": "1090333",
    "ThreadId": "456252",
    "Html": "Thanks for notified me. I correct immediately.<br />\n",
    "PostedDate": "2013-09-09T12:34:37.833-07:00",
    "UserRole": null,
    "MarkedAsAnswerDate": "2013-10-05T05:08:21.633-07:00"
  }
]