{
  "WorkItem": {
    "AffectedComponent": {
      "Name": "",
      "DisplayName": ""
    },
    "ClosedComment": "",
    "ClosedDate": null,
    "CommentCount": 0,
    "Custom": null,
    "Description": "you use assemblies without any know source. \r\nEasyCompany for example. Name the source or tell where to find. \r\n(yes of course i can use the dll form the download but ... yeah, you know....)",
    "LastUpdatedDate": "2017-03-08T09:25:18.5-08:00",
    "PlannedForRelease": "",
    "ReleaseVisibleToPublic": false,
    "Priority": {
      "Name": "Unassigned",
      "Severity": 0,
      "Id": 0
    },
    "ProjectName": "WsusPackagePublisher",
    "ReportedDate": "2017-03-08T09:25:18.5-08:00",
    "Status": {
      "Name": "Proposed",
      "Id": 1
    },
    "ReasonClosed": {
      "Name": "Unassigned"
    },
    "Summary": "source of dependencies",
    "Type": {
      "Name": "Unassigned",
      "Id": 5
    },
    "VoteCount": 1,
    "Id": 363
  },
  "FileAttachments": [],
  "Comments": []
}